FasterKModes/BaseClusterer.py
FasterKModes/FasterKModes.py
FasterKModes/FasterKPrototypes.py
FasterKModes/__init__.py
FasterKModes/config.py
FasterKModes/delete_so.py
FasterKModes/src/common_funcs.c
FasterKModes/src/generate_code.py
FasterKModes/src/generate_prediction_code.py
FasterKModes/src/get_nearest_hamming_dist_uint8.c
FasterKModes/src/hamming_dist_mat_uint8.c
FasterKModes/src/utils_kmodes.py
FasterKModes-0.1.2.dist-info/LICENSE
FasterKModes-0.1.2.dist-info/METADATA
FasterKModes-0.1.2.dist-info/WHEEL
FasterKModes-0.1.2.dist-info/top_level.txt
FasterKModes-0.1.2.dist-info/RECORD
