Metadata-Version: 2.2
Name: FasterKModes
Version: 0.1.2
Summary: Faster Implementation of KModes and KPrototypes.
Home-page: https://github.com/NaoMatch/FasterKModes
Author: NaoMatch
Author-email: mn1491625@gmail.com
License: MIT
Keywords: KModes KPrototypes Machine-Learning Clustering
Classifier: License :: OSI Approved :: MIT License
Classifier: Programming Language :: Python :: 3.10
License-File: LICENSE
Requires-Dist: numpy
Requires-Dist: scipy
Requires-Dist: appdirs
Dynamic: author
Dynamic: author-email
Dynamic: classifier
Dynamic: description
Dynamic: description-content-type
Dynamic: home-page
Dynamic: keywords
Dynamic: license
Dynamic: requires-dist
Dynamic: summary
